{
  "uuid": "5c6c35c9-e58c-47da-bd0d-4011d76a71a4",
  "shortName": "analog-traditional",
  "longName": "analog-traditional",
  "companyName": "MakeAwesomeHappen",
  "versionLabel": "1.0",
  "sdkVersion": "3",
  "targetPlatforms": ["basalt"],
  "watchapp": {
    "watchface": true
  },
  "appKeys": {
    "dummy": 0
  },
  "resources": {
    "media": [
       {
          "characterRegex": "[0-9]",
          "type": "font",
          "name": "SANS_13",
          "file": "estre.ttf"
       }
    ]
  }
}
